{
    "fields": [
        {
            "type": "number",
            "name": "id",
            "internal": false,
            "key": true,
            "oid": "4fe52081-2937-4a40-98bc-078d335ba757",
            "required": true,
            "unique": true,
            "displayLabel": "Id"
        },
        {
            "type": "datetime",
            "name": "creationDate",
            "internal": false,
            "oid": "e1e3a02b-1672-4377-b7f4-e047adf91de7",
            "displayLabel": "Created",
            "historyType": "timeCreated"
        },
        {
            "type": "datetime",
            "name": "lastUpdateDate",
            "internal": false,
            "oid": "0f792827-7680-4ffb-b2a4-07e50cd0f518",
            "displayLabel": "Last Updated",
            "historyType": "timeUpdated"
        },
        {
            "type": "string",
            "name": "createdBy",
            "internal": false,
            "oid": "b2188ea4-40d6-419c-a568-17bae6d10a57",
            "displayLabel": "Created By",
            "historyType": "createdBy"
        },
        {
            "type": "string",
            "name": "lastUpdatedBy",
            "internal": false,
            "oid": "8c4c71ab-38c7-4f60-b3bd-d53237b191ce",
            "displayLabel": "Last Updated By",
            "historyType": "updatedBy"
        },
        {
            "type": "number",
            "name": "versionNumber",
            "internal": false,
            "oid": "18037c70-f96c-41c3-b16e-a2cac8363f6d",
            "displayLabel": "Version Number",
            "historyType": "versionNumber"
        },
        {
            "type": "string",
            "name": "status",
            "oid": "3d7d6de1-5061-4d0b-bbeb-ca17d27cfc75",
            "displayLabel": "status"
        }
    ],
    "name": "ReadinessStatus",
    "oid": "821a1c07-6e89-4351-9428-637cefa45155",
    "security": {
        "type": "local",
        "acl": [
            {
                "roleId": "approle.anonymous.user",
                "privileges": [
                    {
                        "name": "view",
                        "value": true
                    },
                    {
                        "name": "create",
                        "value": true
                    },
                    {
                        "name": "update",
                        "value": true
                    },
                    {
                        "name": "delete",
                        "value": true
                    }
                ]
            },
            {
                "roleId": "approle.authenticated.user",
                "privileges": [
                    {
                        "name": "view",
                        "value": true
                    },
                    {
                        "name": "create",
                        "value": true
                    },
                    {
                        "name": "update",
                        "value": true
                    },
                    {
                        "name": "delete",
                        "value": true
                    }
                ]
            }
        ]
    },
    "displayLabel": "Readiness Status"
}